<SearchParameter xmlns="http://hl7.org/fhir">
  <id value="MII-SearchParameter-ResearchSubject-Consent"/>
  <url value="https://www.medizininformatik-initiative.de/fhir/core/modul-person/SearchParameter/ResearchSubject-Consent"/>
  <version value="2.0.0-alpha3"/>
  <name value="MII_SearchParameter_ResearchSubject_Consent"/>
  <status value="active"/>
  <experimental value="false"/>
  <date value="2022-02-21"/>
  <code value="consent"/>
  <base value="ResearchSubject"/>
  <type value="reference"/>
  <expression value="ResearchSubject.consent"/>
</SearchParameter>