<?xml version="1.0" encoding="utf-8"?>
<StructureDefinition xmlns="http://hl7.org/fhir">
  <id value="ProfileResearchSubjectProbandIn" />
  <url value="https://www.medizininformatik-initiative.de/fhir/core/modul-person/StructureDefinition/ResearchSubject" />
  <version value="1.0.17" />
  <name value="ProfileResearchSubjectProbandIn" />
  <title value="Profile - ResearchSubject - ProbandIn" />
  <status value="active" />
  <description value="Dieses Profil beschreibt eine ProbandIn in der Medizininformatik-Initiative." />
  <fhirVersion value="4.0.1" />
  <kind value="resource" />
  <abstract value="false" />
  <type value="ResearchSubject" />
  <baseDefinition value="http://hl7.org/fhir/StructureDefinition/ResearchSubject" />
  <derivation value="constraint" />
  <differential>
    <element id="ResearchSubject.id">
      <path value="ResearchSubject.id" />
      <mustSupport value="true" />
    </element>
    <element id="ResearchSubject.meta">
      <path value="ResearchSubject.meta" />
      <mustSupport value="true" />
    </element>
    <element id="ResearchSubject.meta.source">
      <path value="ResearchSubject.meta.source" />
      <mustSupport value="true" />
    </element>
    <element id="ResearchSubject.meta.profile">
      <path value="ResearchSubject.meta.profile" />
      <mustSupport value="true" />
    </element>
    <element id="ResearchSubject.identifier">
      <path value="ResearchSubject.identifier" />
      <slicing>
        <discriminator>
          <type value="pattern" />
          <path value="$this" />
        </discriminator>
        <rules value="open" />
      </slicing>
      <min value="1" />
      <mustSupport value="true" />
    </element>
    <element id="ResearchSubject.identifier:subjectIdentificationCode">
      <path value="ResearchSubject.identifier" />
      <sliceName value="subjectIdentificationCode" />
      <min value="1" />
      <max value="1" />
      <patternIdentifier>
        <type>
          <coding>
            <system value="http://terminology.hl7.org/CodeSystem/v2-0203" />
            <code value="ANON" />
          </coding>
        </type>
      </patternIdentifier>
      <mustSupport value="true" />
    </element>
    <element id="ResearchSubject.identifier:subjectIdentificationCode.type">
      <path value="ResearchSubject.identifier.type" />
      <mustSupport value="true" />
    </element>
    <element id="ResearchSubject.identifier:subjectIdentificationCode.system">
      <path value="ResearchSubject.identifier.system" />
      <min value="1" />
      <mustSupport value="true" />
    </element>
    <element id="ResearchSubject.identifier:subjectIdentificationCode.value">
      <path value="ResearchSubject.identifier.value" />
      <min value="1" />
      <mustSupport value="true" />
    </element>
    <element id="ResearchSubject.status">
      <path value="ResearchSubject.status" />
      <mustSupport value="true" />
    </element>
    <element id="ResearchSubject.period">
      <path value="ResearchSubject.period" />
      <min value="1" />
      <mustSupport value="true" />
    </element>
    <element id="ResearchSubject.period.start">
      <path value="ResearchSubject.period.start" />
      <min value="1" />
      <mustSupport value="true" />
    </element>
    <element id="ResearchSubject.period.end">
      <path value="ResearchSubject.period.end" />
      <mustSupport value="true" />
    </element>
    <element id="ResearchSubject.study">
      <path value="ResearchSubject.study" />
      <type>
        <code value="Reference" />
        <profile value="https://www.medizininformatik-initiative.de/fhir/core/StructureDefinition/MII-Reference" />
      </type>
      <mustSupport value="true" />
    </element>
    <element id="ResearchSubject.individual">
      <path value="ResearchSubject.individual" />
      <min value="1" />
      <type>
        <code value="Reference" />
        <profile value="https://www.medizininformatik-initiative.de/fhir/core/StructureDefinition/MII-Reference" />
      </type>
      <mustSupport value="true" />
    </element>
    <element id="ResearchSubject.consent">
      <path value="ResearchSubject.consent" />
      <min value="1" />
      <type>
        <code value="Reference" />
        <profile value="https://www.medizininformatik-initiative.de/fhir/core/StructureDefinition/MII-Reference" />
      </type>
      <mustSupport value="true" />
    </element>
  </differential>
</StructureDefinition>